cliptargets-0.1.3.dist-info/METADATA
cliptargets-0.1.3.dist-info/WHEEL
cliptargets-0.1.3.dist-info/entry_points.txt
cliptargets-0.1.3.dist-info/licenses/LICENSE
cliptargets/__init__.py
cliptargets/cli.py
cliptargets/core.py
cliptargets-0.1.3.dist-info/RECORD
